yg.emanate-0.6.0-py3.6-nspkg.pth
yg/emanate/__init__.py
yg/emanate/events.py
yg/emanate/observers.py
yg.emanate-0.6.0.dist-info/LICENSE.txt
yg.emanate-0.6.0.dist-info/METADATA
yg.emanate-0.6.0.dist-info/RECORD
yg.emanate-0.6.0.dist-info/WHEEL
yg.emanate-0.6.0.dist-info/namespace_packages.txt
yg.emanate-0.6.0.dist-info/top_level.txt
