Metadata-Version: 2.1
Name: yg.emanate
Version: 0.6.0
Summary: Lightweight event system for Python
Home-page: https://github.com/yougov/yg.emanate
Author: YouGov, plc
Author-email: dev@yougov.com
License: UNKNOWN
Platform: UNKNOWN
Classifier: Development Status :: 2 - Pre-Alpha
Classifier: Intended Audience :: Developers
Classifier: License :: OSI Approved :: MIT License
Classifier: Natural Language :: English
Classifier: Programming Language :: Python :: 2.7
Classifier: Programming Language :: Python :: 3
Requires-Python: >=2.7,!=3.0.*,!=3.1.*,!=3.2.*,!=3.3.*
Requires-Dist: blinker
Requires-Dist: jaraco.classes (>=1.1)
Requires-Dist: pika
Requires-Dist: PikaChewie (>=1.3)
Requires-Dist: six
